beast_pype/COVID.py
beast_pype/__init__.py
beast_pype/beast_xml_gen.py
beast_pype/cli.py
beast_pype/date_utilities.py
beast_pype/fig_utils.py
beast_pype/nb_utils.py
beast_pype/outputs.py
beast_pype/report_gen.py
beast_pype/seq_samplers.py
beast_pype/stat_distributions.py
beast_pype/tree_time_scale.py
beast_pype/workflow_params.py
beast_pype/diagnostics/__init__.py
beast_pype/diagnostics/gen_diag_nb.py
beast_pype/diagnostics/mcmc.py
beast_pype/diagnostics/runtime.py
beast_pype/report_templates/BDSKY-Serial-Comparative.ipynb
beast_pype/report_templates/BDSKY-Serial.ipynb
beast_pype/report_templates/COVID-Strain-Surveillance.ipynb
beast_pype/report_templates/Generic-Comparative.ipynb
beast_pype/report_templates/Generic.ipynb
beast_pype/report_templates/__init__.py
beast_pype/workflow_modules/Phase-1-Metadata-and-Sequence-Separation.ipynb
beast_pype/workflow_modules/Phase-2i-IQTree-Building.ipynb
beast_pype/workflow_modules/Phase-2i-IQTree-Correction.ipynb
beast_pype/workflow_modules/Phase-2ii-TreeTime-and-Down-Sampling.ipynb
beast_pype/workflow_modules/Phase-3-Gen-BDSKY-Serial-xml.ipynb
beast_pype/workflow_modules/Phase-3-Gen-Generic-xml.ipynb
beast_pype/workflow_modules/Phase-4-GNU-Parallel-Running-BEAST.ipynb
beast_pype/workflow_modules/Phase-4-SBATCH-Running-BEAST.ipynb
beast_pype/workflow_modules/Phase-5-Diagnosing-Outputs-and-Generate-Report.ipynb
beast_pype/workflow_modules/Phase-5-Diagnosing-Runtime-and-Resource-Usage.ipynb
beast_pype/workflow_modules/Phase-5-Diagnosing-XML-sets-and-Generate-Report.ipynb
beast_pype/workflow_modules/Phase-5i-Merge-BEAST-outputs.ipynb
beast_pype/workflow_modules/Phase-5ii-Gen-MCC-Trees.ipynb
beast_pype/workflow_modules/__init__.py
beast_pype/workflows/BDSKY-Serial-Comparative.ipynb
beast_pype/workflows/BDSKY-Serial.ipynb
beast_pype/workflows/COVID-Strain-Surveillance.ipynb
beast_pype/workflows/Generic-Comparative.ipynb
beast_pype/workflows/Generic.ipynb
beast_pype/workflows/Optimising-BEAST-Runs.ipynb
beast_pype-0.2.0.dist-info/licenses/LICENSE
beast_pype-0.2.0.dist-info/METADATA
beast_pype-0.2.0.dist-info/WHEEL
beast_pype-0.2.0.dist-info/entry_points.txt
beast_pype-0.2.0.dist-info/top_level.txt
beast_pype-0.2.0.dist-info/RECORD
