Metadata-Version: 2.4
Name: beast_pype
Version: 0.2.0
Summary: A package of BEAST 2 pipelines for phylodynamics.
Author-email: Martin Grunnill <Martin.Grunnill@phac-aspc.gc.ca>, Carmen Lia Murall <Carmen.Lia.Murall@phac-aspc.gc.ca>
Maintainer-email: Martin Grunnill <Martin.Grunnill@phac-aspc.gc.ca>, Carmen Lia Murall <Carmen.Lia.Murall@phac-aspc.gc.ca>
License: 
Project-URL: Homepage, https://github.com/m-d-grunnill/BEAST_pype
Project-URL: Repository, https://github.com/m-d-grunnill/BEAST_pype
Project-URL: Issues, https://github.com/m-d-grunnill/BEAST_pype/issues
Project-URL: Documentaion, https://github.com/m-d-grunnill/BEAST_pype/wiki
Keywords: Phylodynamics,Epimediology,Ecology,Virology,Genomics
Classifier: Programming Language :: Python :: 3.10
Classifier: Intended Audience :: Science/Research
Classifier: Topic :: Scientific/Engineering
Requires-Python: >=3.10
License-File: LICENSE
Requires-Dist: arviz
Requires-Dist: bash_kernel
Requires-Dist: beast2-xml>=1.4.1
Requires-Dist: biopython
Requires-Dist: click
Requires-Dist: dark-matter
Requires-Dist: ete3
Requires-Dist: ipykernel
Requires-Dist: ipywidgets
Requires-Dist: jupyter
Requires-Dist: matplotlib
Requires-Dist: nbconvert
Requires-Dist: nbformat
Requires-Dist: numpy
Requires-Dist: pandas
Requires-Dist: papermill
Requires-Dist: phylo-treetime
Requires-Dist: python-dateutil
Requires-Dist: pyyaml
Requires-Dist: scipy
Requires-Dist: seaborn
Requires-Dist: xarray
Dynamic: license-file
Dynamic: requires-dist
